[{"ein": "631242599", "charityName": "SHEPHERDS LIGHT HARVEST OUTREACH", "url": "http://www.orghunter.com/organization/631242599", "donationUrl": "http://donate.makemydonation.org/donate/631242599", "city": "HINESVILLE", "state": "Georgia", "zipCode": "31313-7159", "start": 0, "rows": 20, "recordCount": 70933, "score": 1, "acceptingDonations": 0, "category": "Not Provided", "eligibleCd": 0, "deductibilityCd": 0, "statusCd": 4, "website": "", "missionStatement": "", "parent_ein": 1, "longitude": "-81.643837", "latitude": "31.840656"}, {"ein": "581090387", "charityName": "ARBOR MONTESSORI SCHOOL INC", "url": "http://www.orghunter.com/organization/581090387", "donationUrl": "http://donate.makemydonation.org/donate/581090387", "city": "DECATUR", "state": "Georgia", "zipCode": "30033-1308", "start": 0, "rows": 20, "recordCount": 70933, "score": 1, "acceptingDonations": 1, "category": "Educational Institutions and Related Activities", "eligibleCd": 1, "deductibilityCd": 1, "statusCd": 1, "website": "", "missionStatement": "", "parent_ein": 1, "longitude": "-84.284721", "latitude": "33.826031"}, {"ein": "800024053", "charityName": "AFRICAN PERFORMING ARTS ASSOCIATION GINE NYI RA INC", "url": "http://www.orghunter.com/organization/800024053", "donationUrl": "http://donate.makemydonation.org/donate/800024053", "city": "ATLANTA", "state": "Georgia", "zipCode": "30366-7173", "start": 0, "rows": 20, "recordCount": 70933, "score": 1, "acceptingDonations": 1, "category": "Arts, Culture and Humanities", "eligibleCd": 1, "deductibilityCd": 1, "statusCd": 1, "website": "", "missionStatement": "", "parent_ein": 1, "longitude": "-84.298462", "latitude": "33.895916"}, {"ein": "611534629", "charityName": "INTERNATIONAL ASSOCIATION OF", "url": "http://www.orghunter.com/organization/611534629", "donationUrl": "http://donate.makemydonation.org/donate/611534629", "city": "ATLANTA", "state": "Georgia", "zipCode": "30303-8819", "start": 0, "rows": 20, "recordCount": 70933, "score": 1, "acceptingDonations": 0, "category": "Not Provided", "eligibleCd": 0, "deductibilityCd": 0, "statusCd": 4, "website": "", "missionStatement": "", "parent_ein": 1, "longitude": "-84.388374", "latitude": "33.755711"}, {"ein": "582042454", "charityName": "NEW DIRECTION CHRISTIAN MINISTRIES", "url": "http://www.orghunter.com/organization/582042454", "donationUrl": "http://donate.makemydonation.org/donate/582042454", "city": "DECATUR", "state": "Georgia", "zipCode": "30030-4471", "start": 0, "rows": 20, "recordCount": 70933, "score": 1, "acceptingDonations": 0, "category": "Not Provided", "eligibleCd": 0, "deductibilityCd": 0, "statusCd": 4, "website": "", "missionStatement": "", "parent_ein": 1, "longitude": "-84.286835", "latitude": "33.751259"}, {"ein": "273355731", "charityName": "SERTOMA INC", "url": "http://www.orghunter.com/organization/273355731", "donationUrl": "http://donate.makemydonation.org/donate/273355731", "city": "ALBANY", "state": "Georgia", "zipCode": "31702-1301", "start": 0, "rows": 20, "recordCount": 70933, "score": 1, "acceptingDonations": 1, "category": "Not Provided", "eligibleCd": 1, "deductibilityCd": 1, "statusCd": 1, "website": "", "missionStatement": "", "parent_ein": 1, "longitude": "-84.160004", "latitude": "31.580000"}, {"ein": "264058353", "charityName": "HEERY INTERNATIONAL FOUNDATION INC", "url": "http://www.orghunter.com/organization/264058353", "donationUrl": "http://donate.makemydonation.org/donate/264058353", "city": "ATLANTA", "state": "Georgia", "zipCode": "30309-3915", "start": 0, "rows": 20, "recordCount": 70933, "score": 1, "acceptingDonations": 0, "category": "Philanthropy, Voluntarism and Grantmaking Foundations", "eligibleCd": 0, "deductibilityCd": 1, "statusCd": 0, "website": "", "missionStatement": "", "parent_ein": 1, "longitude": "-84.383629", "latitude": "33.781166"}, {"ein": "582559217", "charityName": "REVIVAL PRAYER INSTITUTE INC", "url": "http://www.orghunter.com/organization/582559217", "donationUrl": "http://donate.makemydonation.org/donate/582559217", "city": "LILBURN", "state": "Georgia", "zipCode": "30048-2084", "start": 0, "rows": 20, "recordCount": 70933, "score": 1, "acceptingDonations": 1, "category": "Religion-Related, Spiritual Development", "eligibleCd": 1, "deductibilityCd": 1, "statusCd": 1, "website": "", "missionStatement": "", "parent_ein": 1, "longitude": "-84.110001", "latitude": "33.869999"}, {"ein": "452521351", "charityName": "BRAIN INJURY ADVOCATE SERVICES OF GEORGIA INC", "url": "http://www.orghunter.com/organization/452521351", "donationUrl": "http://donate.makemydonation.org/donate/452521351", "city": "VALDOSTA", "state": "Georgia", "zipCode": "31602-2374", "start": 0, "rows": 20, "recordCount": 70933, "score": 1, "acceptingDonations": 1, "category": "Health - General and Rehabilitative", "eligibleCd": 1, "deductibilityCd": 1, "statusCd": 1, "website": "", "missionStatement": "", "parent_ein": 1, "longitude": "-83.304497", "latitude": "30.856001"}, {"ein": "911823211", "charityName": "CRISTO PARA TODAS LAS NACIONES IGLESIA PRESBITERIANA USA INC", "url": "http://www.orghunter.com/organization/911823211", "donationUrl": "http://donate.makemydonation.org/donate/911823211", "city": "ATLANTA", "state": "Georgia", "zipCode": "30345-1342", "start": 0, "rows": 20, "recordCount": 70933, "score": 1, "acceptingDonations": 1, "category": "Not Provided", "eligibleCd": 1, "deductibilityCd": 1, "statusCd": 1, "website": "", "missionStatement": "", "parent_ein": 1, "longitude": "-84.281631", "latitude": "33.857433"}, {"ein": "586122685", "charityName": "GEORGIA EXTENSION 4-H FOUNDATION", "url": "http://www.orghunter.com/organization/586122685", "donationUrl": "http://donate.makemydonation.org/donate/586122685", "city": "GREENSBORO", "state": "Georgia", "zipCode": "30642-2765", "start": 0, "rows": 20, "recordCount": 70933, "score": 1, "acceptingDonations": 1, "category": "Not Provided", "eligibleCd": 1, "deductibilityCd": 1, "statusCd": 1, "website": "", "missionStatement": "", "parent_ein": 1, "longitude": "-83.193405", "latitude": "33.566132"}, {"ein": "436906587", "charityName": "JOHN P AND MARTHA D HUMPHREYS CHARITABLE FOUNDATION", "url": "http://www.orghunter.com/organization/436906587", "donationUrl": "http://donate.makemydonation.org/donate/436906587", "city": "RICHMOND HILL", "state": "Georgia", "zipCode": "31324-4393", "start": 0, "rows": 20, "recordCount": 70933, "score": 1, "acceptingDonations": 0, "category": "Philanthropy, Voluntarism and Grantmaking Foundations", "eligibleCd": 0, "deductibilityCd": 1, "statusCd": 4, "website": "", "missionStatement": "", "parent_ein": 1, "longitude": "-81.289444", "latitude": "31.924101"}, {"ein": "911995965", "charityName": "TROUT UNLIMITED", "url": "http://www.orghunter.com/organization/911995965", "donationUrl": "http://donate.makemydonation.org/donate/911995965", "city": "BLUE RIDGE", "state": "Georgia", "zipCode": "30513-0049", "start": 0, "rows": 20, "recordCount": 70933, "score": 1, "acceptingDonations": 1, "category": "Not Provided", "eligibleCd": 1, "deductibilityCd": 1, "statusCd": 1, "website": "", "missionStatement": "", "parent_ein": 1, "longitude": "-84.249483", "latitude": "34.922129"}, {"ein": "581348942", "charityName": "NATIONAL ASSOCIATION OF THE REMODELING INDUSTRY INC", "url": "http://www.orghunter.com/organization/581348942", "donationUrl": "http://donate.makemydonation.org/donate/581348942", "city": "ATLANTA", "state": "Georgia", "zipCode": "30340-3702", "start": 0, "rows": 20, "recordCount": 70933, "score": 1, "acceptingDonations": 0, "category": "Not Provided", "eligibleCd": 0, "deductibilityCd": 2, "statusCd": 0, "website": "", "missionStatement": "", "parent_ein": 1, "longitude": "-84.265725", "latitude": "33.886116"}, {"ein": "263883825", "charityName": "DECATUR TOURISM BUREAU INC", "url": "http://www.orghunter.com/organization/263883825", "donationUrl": "http://donate.makemydonation.org/donate/263883825", "city": "DECATUR", "state": "Georgia", "zipCode": "30030-3309", "start": 0, "rows": 20, "recordCount": 70933, "score": 1, "acceptingDonations": 0, "category": "Community Improvement, Capacity Building", "eligibleCd": 0, "deductibilityCd": 2, "statusCd": 0, "website": "", "missionStatement": "", "parent_ein": 1, "longitude": "-84.296104", "latitude": "33.773720"}, {"ein": "581537133", "charityName": "BUCHANAN FIRST BAPTIST CHURCH", "url": "http://www.orghunter.com/organization/581537133", "donationUrl": "http://donate.makemydonation.org/donate/581537133", "city": "BUCHANAN", "state": "Georgia", "zipCode": "30113-0485", "start": 0, "rows": 20, "recordCount": 70933, "score": 1, "acceptingDonations": 1, "category": "Not Provided", "eligibleCd": 1, "deductibilityCd": 1, "statusCd": 1, "website": "", "missionStatement": "", "parent_ein": 1, "longitude": "-85.210129", "latitude": "33.859901"}, {"ein": "581466484", "charityName": "PLAINFIELD BAPTIST CHURCH", "url": "http://www.orghunter.com/organization/581466484", "donationUrl": "http://donate.makemydonation.org/donate/581466484", "city": "PLAINFIELD", "state": "Georgia", "zipCode": "31023-3057", "start": 0, "rows": 20, "recordCount": 70933, "score": 1, "acceptingDonations": 1, "category": "Not Provided", "eligibleCd": 1, "deductibilityCd": 1, "statusCd": 1, "website": "", "missionStatement": "", "parent_ein": 1, "longitude": "-83.111320", "latitude": "32.287987"}, {"ein": "237394832", "charityName": "DEPT OF GEORGIA LADIES AUXILIARY TO THE VFW OF THE UNITED STATES", "url": "http://www.orghunter.com/organization/237394832", "donationUrl": "http://donate.makemydonation.org/donate/237394832", "city": "COLUMBUS", "state": "Georgia", "zipCode": "31901-3445", "start": 0, "rows": 20, "recordCount": 70933, "score": 1, "acceptingDonations": 0, "category": "Public, Society Benefit - Multipurpose and Other", "eligibleCd": 0, "deductibilityCd": 2, "statusCd": 0, "website": "", "missionStatement": "", "parent_ein": 1, "longitude": "-84.970337", "latitude": "32.442814"}, {"ein": "582482650", "charityName": "KOREAN ENTERTAINMENT ASSOCIATION OF", "url": "http://www.orghunter.com/organization/582482650", "donationUrl": "http://donate.makemydonation.org/donate/582482650", "city": "DULUTH", "state": "Georgia", "zipCode": "30096-7722", "start": 0, "rows": 20, "recordCount": 70933, "score": 1, "acceptingDonations": 0, "category": "Not Provided", "eligibleCd": 0, "deductibilityCd": 0, "statusCd": 4, "website": "", "missionStatement": "", "parent_ein": 1, "longitude": "-84.146294", "latitude": "33.993664"}, {"ein": "586043617", "charityName": "INTERNATIONAL ASSOCIATION OF", "url": "http://www.orghunter.com/organization/586043617", "donationUrl": "http://donate.makemydonation.org/donate/586043617", "city": "ADEL", "state": "Georgia", "zipCode": "31620-3630", "start": 0, "rows": 20, "recordCount": 70933, "score": 1, "acceptingDonations": 0, "category": "Not Provided", "eligibleCd": 0, "deductibilityCd": 0, "statusCd": 4, "website": "", "missionStatement": "", "parent_ein": 1, "longitude": "-83.413818", "latitude": "31.127493"}]